README.rst
setup.cfg
setup.py
action_log/__init__.py
action_log/admin.py
action_log/models.py
action_log/tests.py
action_log/views.py
action_log/migrations/0001_initial.py
action_log/migrations/__init__.py
django_action_log.egg-info/PKG-INFO
django_action_log.egg-info/SOURCES.txt
django_action_log.egg-info/dependency_links.txt
django_action_log.egg-info/pbr.json
django_action_log.egg-info/top_level.txt