Metadata-Version: 1.1
Name: django-action-log
Version: 0.1
Summary: Simple and small action logger for django.
Home-page: https://github.com/bradojevic/django-action-log
Author: Bojan Radojevic
Author-email: bradojevic@gmail.com
License: MIT License
Download-URL: https://github.com/bradojevic/django-action-log/tarball/0.1
Platform: UNKNOWN
Classifier: Environment :: Web Environment
Classifier: Framework :: Django
Classifier: Intended Audience :: Developers
Classifier: License :: OSI Approved :: MIT License
Classifier: Operating System :: OS Independent
Classifier: Programming Language :: Python
Classifier: Topic :: Internet :: WWW/HTTP
Classifier: Topic :: Internet :: WWW/HTTP :: Dynamic Content
